LICENSE
MANIFEST.in
README.md
pyproject.toml
setup.py
anyBSM/Delta_r_SM.py
anyBSM/__init__.py
anyBSM/anyBSM.py
anyBSM/anyEWPO.py
anyBSM/anyH3.py
anyBSM/anyModel.py
anyBSM/anyPerturbativeUnitarity.py
anyBSM/anyProcess.py
anyBSM/config.py
anyBSM/diagrams.py
anyBSM/loopfunctions.py
anyBSM/physic_utils.py
anyBSM/plotting.py
anyBSM/topologies.py
anyBSM/utils.py
anyBSM.egg-info/PKG-INFO
anyBSM.egg-info/SOURCES.txt
anyBSM.egg-info/dependency_links.txt
anyBSM.egg-info/requires.txt
anyBSM.egg-info/top_level.txt
anyBSM/PDFs/parton_luminosities-PDF4LHC15_nlo_mc-Q400.h5
anyBSM/latex/__init__.py
anyBSM/latex/drawer.py
anyBSM/latex/printer.py
anyBSM/latex/tikzfeynman/LICENSE
anyBSM/latex/tikzfeynman/tikzfeynman.keys.code.tex
anyBSM/latex/tikzfeynman/tikzfeynman.patch.3.0.0.lua
anyBSM/latex/tikzfeynman/tikzfeynman.patch.3.0.1.lua
anyBSM/latex/tikzfeynman/tikzfeynman.sty
anyBSM/latex/tikzfeynman/tikzlibraryfeynman.code.tex
anyBSM/logos/anyH3_logo.pdf
anyBSM/logos/anyH3_logo_large.png
anyBSM/logos/anyH3_logo_plot.png
anyBSM/logos/anyH3_logo_small.png
anyBSM/logos/class_structure.png
anyBSM/logos/program_structure.png
anyBSM/mathematica_interface/anyBSM.m
anyBSM/ufo/__init__.py
anyBSM/ufo/function_library.py
anyBSM/ufo/object_library.py
anyBSM/ufo/write_param_card.py
bin/anyBSM
bin/anyBSM_import
tests/test_SM.py
tests/test_THDM.py
tests/test_caching.py
tests/test_loopfunctions.py
tests/test_tadpoles.py
tests/test_unitarity.py